{
  "metadata": {
    "date": "2025-11-30T14:30:22",
    "timestamp": "20251130_143022",
    "version": "2.0.0"
  },
  "mode": "PvE",
  "joueur1": {
    "nom": "🔮 Sorcière",
    "classe": "Sorceress",
    "est_humain": true
  },
  "joueur2": {
    "nom": "🧙 Sage",
    "classe": "Sage",
    "est_humain": false,
    "ia_difficulte": "normal"
  },
  "vainqueur": {
    "nom": "🔮 Sorcière",
    "classe": "Sorceress"
  },
  "nombre_tours": 12,
  "joueur1_final": {
    "hp": 234,
    "hp_max": 1000,
    "mp": 120,
    "mp_max": 500,
    "degats_infliges": 1145,
    "degats_recus": 766,
    "coups_critiques": 3,
    "skills_utilises": {
      "Dark Flame": 4,
      "Midnight Stinger": 3,
      "Violation": 2,
      "Shadow Eruption": 1,
      "Rushing Crow": 1,
      "Dream of Doom": 1
    }
  },
  "joueur2_final": {
    "hp": 0,
    "hp_max": 1100,
    "mp": 85,
    "mp_max": 450,
    "degats_infliges": 766,
    "degats_recus": 1145,
    "coups_critiques": 2,
    "skills_utilises": {
      "Ator's Rift": 5,
      "Sages' Memory": 2,
      "Apocryphal Gate": 1,
      "Concentrated Magic": 2,
      "Prime: Ator's Promise": 1,
      "Blink": 1
    }
  },
  "historique_tours": [
    {
      "tour": 1,
      "attaquant": "🔮 Sorcière",
      "skill": "Dark Flame",
      "degats": 102,
      "critique": false,
      "esquive": false
    },
    {
      "tour": 2,
      "attaquant": "🧙 Sage",
      "skill": "Ator's Rift",
      "degats": 88,
      "critique": false,
      "esquive": false
    }
  ]
}
